Workbook

Sheet How to Use
B1: How to Use This Pricing Calculator
B3: 1. Getting a Quote
B4: • Go to the Pricing Calculator tab.
B5: • Enter the Pet Name at the top of Pet Information - this is what gets saved to the Booking Log if you use the Save button (see section 6).
B6: • Select Species, Coat/Hair Type, Size, and whether the pet is a senior.
B7: • Optionally type the breed if known — this strengthens safety warnings (see below).
B8: • For dogs, optionally pick a Standard Service (Profile Cut, Puppy Cut, Shave Down, or Deshedding). Standard Services are not available for cats.
B9: • Check off any Premium Add-Ons the customer wants.
B10: • If needed, select a De-Matting time bracket, a Discount, or the Seasonal Holiday Package.
B11: • The Total Price and Estimated Groom Time update automatically at the bottom right.
B13: 2. Safety Reminders
B14: • If Shave Down is selected on a coat type where it's not recommended, a warning appears automatically.
... B91: • Groom time estimates are based on general rules (base time + add-ons) and may vary for individual pets — use the 'Add extra time?' toggle if a specific appointment runs long.

Sheet Receipt
C2: Pawfect Mobile Grooming
C3: Grooming Receipt
C5: Date: | D5: =TEXT(TODAY(),"mmmm d, yyyy") -> September 13, 2026
B7: CLIENT & PET DETAILS
B8: Pet Name: | C8: =IF('Pricing Calculator'!F4="","—",'Pricing Calculator'!F4) -> —
B9: Species: | C9: =IF('Pricing Calculator'!B4="","—",'Pricing Calculator'!B4) -> —
B10: Coat Type / Breed: | C10: =IF('Pricing Calculator'!B5="","—",'Pricing Calculator'!B5) -> —
B11: Size: | C11: =IF('Pricing Calculator'!B6="","—",'Pricing Calculator'!B6) -> —
B12: Senior Pet: | C12: =IF('Pricing Calculator'!B7="","—",'Pricing Calculator'!B7) -> —
B14: SERVICE SUMMARY
B15: Item | D15: Amount
B16: Base Groom | D16: ='Pricing Calculator'!J5 -> 0
B17: Age Surcharge | D17: ='Pricing Calculator'!J6 -> 0
B18: Standard/Cat Service | D18: ='Pricing Calculator'!J7 -> 0
B19: Premium Add-Ons | D19: ='Pricing Calculator'!J11 -> 0
B20: De-Matting | D20: ='Pricing Calculator'!J12 -> 0
B21: Seasonal Holiday Package | D21: ='Pricing Calculator'!J13 -> 0
B22: Discount Applied | D22: =-'Pricing Calculator'!J15 -> 0
B24: TOTAL PRICE | D24: ='Pricing Calculator'!J17 -> 0
B25: Estimated Groom Time: | C25: ='Pricing Calculator'!J18 -> 0 min
B27: Thank you for choosing Pawfect! 🐾

Sheet Pricing Calculator
D1: PRICING CALCULATOR | L1: 🐶 | M1: ❤️ | N1: 🛁
A3: 🐾 1. PET INFORMATION | H3: 📋 5. PRICING SUMMARY
A4: Species (Dog/Cat) | E4: Pet Name | H4: Item | I4: Details | J4: Amount | K4: Time (min) | N4: =IF(COUNTIF(Data!$A$118:$A$314,B5)>0,INDEX(Data!$B$118:$B$314,MATCH(B5,Data!$A$118:$A$314,0)),B5) -> 0
A5: =IF(B4="Cat","Hair Type","Coat Type / Breed") -> Coat Type / Breed | H5: Base Groom Price | I5: =IF(AND(N4="",B6=""),"—",N4&" / "&B6) -> — | J5: =IF(OR(B4="",N4="",B6=""),0,ROUND(IF(B4="Dog",Data!$B$2,Data!$E$2)*IFERROR(IFERROR(INDEX(Data!$B$7:$B$16,MATCH(N4,Data!$A$7:$A$16,0)),INDEX(Data!$B$21:$B$22,MATCH(N4,Data!$A$21:$A$22,0))),0)*IFERROR(INDEX(Data!$C$27:$C$31,MATCH(B6,Data!$A$27:$A$31,0)),1),0)) -> 0 | K5: =IF(B4="",0,IF(B4="Dog",Data!$B$3,IF(Data!$E$3="⚠ TBD",0,Data!$E$3))) -> 0
A6: Size | H6: Age Surcharge (Base Groom) | I6: =IF(B7="Yes","Senior pet","—") -> — | J6: =IF(B7="Yes",IF(B4="Dog",Data!$B$36,Data!$B$37),0) -> 0 | K6: =IF(B7="Yes",15,0) -> 0
A7: Senior Pet? (10+ dog / 12+ cat) | H7: Standard Service Fee | I7: =IF(B4="Dog",IF(B10="","None selected",B10),IF(B4="Cat",IF(B13="","None selected",B13),"None selected")) -> None selected | J7: =IF(B4="Dog",IF(B10="",0,ROUND(Data!$H$1*IFERROR(INDEX(Data!$B$7:$B$16,MATCH(N4,Data!$A$7:$A$16,0)),1),0)+IF(B10="Profile Cut",7,0)),IF(B4="Cat",IFERROR(INDEX(Data!$B$109:$B$113,MATCH(B13,Data!$A$109:$A$113,0)),0),0)) -> 0 | K7: =IF(B4="Dog",IF(B10="",0,30),IF(B4="Cat",IF(B13="",0,30),0)) -> 0
A9: ✂️ 2. SERVICE SELECTION | H9: Base Total | J9: =J5+J6+J7 -> 0 | K9: =K5+K6+K7 -> 0
A10: Standard Service (optional)
A11: =IF(AND(B4="Cat",B10<>""),"⚠ Standard Services (Profile Cut, Puppy Cut, Shave Down, Deshedding) are not offered for cats — please clear this selection.",IF(AND(B4="Dog",B13<>""),"⚠ Cat-Specific Services are not offered for dogs — please clear this selection.",IF(AND(B10="Shave Down",ISNUMBER(SEARCH("husky",B5))),"🛑 DO NOT SHAVE — Husky detected. Use Profile Cut (light tidy) instead. Huskies should never be fully shaved.",IF(AND(B10="Shave Down",COUNTIF(Data!$A$50:$A$54,N4)>0),"⚠ Shave Down is not recommended for this coat type — Profile Cut is the safe alternative for double-coated/feathered breeds.",IF(AND(B10="Shave Down",N4="Short Double Coat",NOT(ISNUMBER(SEARCH("husky",B5)))),"⚠ Reminder: if this is a Husky, select it by name above instead of just the coat type, to get a stronger warning.",""))))) | H11: Add-Ons Total | I11: =SUMPRODUCT((A16:A33<>"")*1)&" selected" -> 0 selected | J11: =SUMPRODUCT((A16:A33<>"")*D16:D33) -> 0 | K11: =SUMPRODUCT((A16:A33<>"")*Data!$C$60:$C$77) -> 0
H12: De-Matting Estimate | I12: =IF(B35="","None",B35) -> None | J12: =IFERROR(INDEX(Data!$B$82:$B$85,MATCH(B35,Data!$A$82:$A$85,0)),0) -> 0 | K12: =IFERROR(INDEX(Data!$C$82:$C$85,MATCH(B35,Data!$A$82:$A$85,0)),0) -> 0
A13: Cat Service (optional) | H13: Seasonal Holiday Package | I13: =IF(B41="Yes","Applied","—") -> — | J13: =IF(B41="Yes",Data!$B$90,0) -> 0 | K13: 0
A14: ➕ 3. PREMIUM ADD-ONS | H14: Subtotal | I14: =IF(B36="Yes","+30 min groomer override applied","") | J14: =J9+J11+J12+J13 -> 0 | K14: =K9+K11+K12+IF(B36="Yes",30,0) -> 0
A15: Select | B15: Add-On Service | D15: Fee | E15: Time | H15: Discount Applied | I15: =IF(B39="","None",IF(B38="Percentage",B39&"%","$"&B39&" fixed")) -> 0% | J15: =IF(OR(B39="",B38=""),0,IF(B38="Percentage",J14*B39/100,MIN(B39,J14))) -> 0 | K15: 0
B16: =Data!A60 -> Hot Aloe SPA Treatment (0-30 lbs) | D16: =Data!B60 -> 20 | E16: =IF(Data!C60=0,"—",Data!C60&" min") -> 15 min
B17: =Data!A61 -> Hot Aloe SPA Treatment (31-60 lbs) | D17: =Data!B61 -> 25 | E17: =IF(Data!C61=0,"—",Data!C61&" min") -> 15 min | H17: 📋 TOTAL PRICE | J17: =ROUND(MAX(J14-J15,0),0) -> 0
B18: =Data!A62 -> Hot Aloe SPA Treatment (60+ lbs) | D18: =Data!B62 -> 30 | E18: =IF(Data!C62=0,"—",Data!C62&" min") -> 15 min | H18: 🕐 ESTIMATED GROOM TIME | J18: =IF(K14<60,K14&" min",INT(K14/60)&" hr "&MOD(K14,60)&" min") -> 0 min
B19: =Data!A63 -> De-Shedding Treatment (0-30 lbs) | D19: =Data!B63 -> 20 | E19: =IF(Data!C63=0,"—",Data!C63&" min") -> 15 min
B20: =Data!A64 -> De-Shedding Treatment (30-60 lbs) | D20: =Data!B64 -> 25 | E20: =IF(Data!C64=0,"—",Data!C64&" min") -> 15 min
B21: =Data!A65 -> De-Shedding Treatment (60-100 lbs) | D21: =Data!B65 -> 30 | E21: =IF(Data!C65=0,"—",Data!C65&" min") -> 15 min
B22: =Data!A66 -> De-Shedding Treatment (101+ lbs) | D22: =Data!B66 -> 40 | E22: =IF(Data!C66=0,"—",Data!C66&" min") -> 15 min
B23: =Data!A67 -> Flea Clean-Up & Van Fumigation | D23: =Data!B67 -> 30 | E23: =IF(Data!C67=0,"—",Data!C67&" min") -> 15 min
B24: =Data!A68 -> Flea Elimination Shampoo | D24: =Data!B68 -> 20 | E24: =IF(Data!C68=0,"—",Data!C68&" min") -> 15 min
B25: =Data!A69 -> Flea & Tick Treatment Drops | D25: =Data!B69 -> 30 | E25: =IF(Data!C69=0,"—",Data!C69&" min") -> 15 min
B26: =Data!A70 -> Flea Removal | D26: =Data!B70 -> 20 | E26: =IF(Data!C70=0,"—",Data!C70&" min") -> 15 min
B27: =Data!A71 -> Nail Trim - Extra (Dog) | D27: =Data!B71 -> 10 | E27: =IF(Data!C71=0,"—",Data!C71&" min") -> 15 min
B28: =Data!A72 -> Paw Pad Treatment | D28: =Data!B72 -> 10 | E28: =IF(Data!C72=0,"—",Data!C72&" min") -> 15 min
B29: =Data!A73 -> Teeth Brushing (Dogs Only) | D29: =Data!B73 -> 10 | E29: =IF(Data!C73=0,"—",Data!C73&" min") -> 15 min
B30: =Data!A74 -> Nail Trim - Extra (Cat) | D30: =Data!B74 -> 10 | E30: =IF(Data!C74=0,"—",Data!C74&" min") -> 15 min
... B33: =Data!A77 -> Whitening Shampoo | D33: =Data!B77 -> 10 | E33: =IF(Data!C77=0,"—",Data!C77&" min") -> 15 min
A35: De-Matting (if needed)
A36: Add extra time? (groomer judgment, +30 min) | B36: No
A37: 🏷️ 4. DISCOUNT
A38: Discount Type | B38: Percentage
A39: Discount Value | B39: 0 | D39: =IF(B38="Percentage","%","$") -> %
A41: Apply Seasonal Holiday Package? | B41: No
A43: 🐾 Open items pending client confirmation: cat base groom time, whether age surcharge applies to Premium Add-ons too, final Profile Cut coat-type list + Husky exception, and Seasonal Holiday Package price (currently $0 — update on Data tab once received).

Sheet Booking Log
A1: Booking Log
A2: Add one row per confirmed appointment. This becomes your running record of bookings and revenue.
A4: Date | B4: Client Name | C4: Pet Name | D4: Species | E4: Coat / Hair Type | F4: Size | G4: Standard Service | H4: Add-Ons | I4: Discount | J4: Total Price | K4: Paid (Y/N) | L4: Notes
A5: 2026-09-05 | B5: Sarah Malik | C5: Bella | D5: Dog | E5: Long Double Coat | F5: Large | G5: Profile Cut | H5: Hot Aloe SPA Treatment | I5: 10% | J5: 175 | K5: Yes | L5: Regular client, every 6 weeks
A6: 2026-09-06 | B6: James Cole | C6: Rocky | D6: Dog | E6: Smooth Coat | F6: Large | I6: 0% | J6: 113 | K6: Yes
A7: 2026-09-08 | B7: Aisha Raza | C7: Coco | D7: Dog | E7: Doodle / Mixed Wool Coat | F7: Large | G7: Profile Cut | H7: De-Shedding Treatment | I7: 0% | J7: 220 | K7: No | L7: Invoice sent, awaiting payment
A8: 2026-09-09 | B8: Tom Reed | C8: Max | D8: Cat | E8: Long Hair | F8: Small | H8: Nail Trim - Extra (Cat) | I8: 0% | J8: 138 | K8: Yes | L8: Senior cat, +$6 surcharge applied
A9: 2026-09-10 | B9: Linda Cruz | C9: Milo | D9: Dog | E9: Short Double Coat | F9: Small | I9: 15% | J9: 96 | K9: Yes
A26: Quick Summary
A27: Total Bookings | B27: =COUNT(J5:J24) -> 5
A28: Total Revenue (All) | B28: =SUM(J5:J24) -> 742
A29: Revenue Collected (Paid = Y) | B29: =SUMIF(K5:K24,"Yes",J5:J24) -> 522
A30: Outstanding (Paid = N) | B30: =SUMIF(K5:K24,"No",J5:J24) -> 220

Sheet Data
A1: REFERENCE DATA (sample figures for demo purposes) | G1: Standard Service Base Price: | H1: 20
A2: Dog Base Groom Price: | B2: 100 | D2: Cat Base Groom Price: | E2: 110 | J2: Affenpinscher
A3: Dog Base Groom Time (flat, all coat types): | B3: 90 | D3: Cat Base Groom Time: | E3: 90 | J3: Afghan
J4: Airedale Terrier
A5: DOG COAT TYPES | J5: Akita
A6: Coat Type | B6: Multiplier | J6: Alaskan Malamute
A7: Hairless | B7: 1 | J7: American Eskimo
A8: Smooth Coat | B8: 1 | J8: American Eskimo Miniature
A9: Short Double Coat | B9: 1.03 | J9: American Pit Bull Terrier
A10: Wire Coat | B10: 1.03 | J10: American Staffordshire Terrier
A11: Silky / Drop Coat | B11: 1.03 | J11: American Stratford Terrier
A12: Long Feathered Sporting / Spaniel Coat | B12: 1.09 | J12: Anatolian Shepherd
A13: Curly / Wool Coat | B13: 1.11 | J13: Aussiedoodle
A14: Single-layered Curly/Woolly Coat | B14: 1.07 | J14: Australian (American) Shepherd Miniature
A15: Long Double Coat | B15: 1.2 | J15: Australian Shepherd
A16: Doodle / Mixed Wool Coat | B16: 1.27 | J16: Australian Terrier
J17: Basenji
J18: Basset Hound
A19: CAT HAIR TYPES | J19: Beagle
A20: Hair Type | B20: Multiplier | J20: Bearded Collie
A21: Short Hair | B21: 1 | J21: Bedlington Terrier
A22: Long Hair | B22: 1.07 | J22: Belgian Malinois
J23: Belgian Shepherd (AKA Sheepdog)
J24: Bernese Mountain Dog
A25: SIZES | J25: Bernie Doodle
A26: Size | B26: Weight Range | C26: Multiplier | J26: Bichon Frise
A27: Small (0-20 lbs) | B27: 0-20 lbs | C27: 1 | J27: Bichpoo
A28: Medium (21-35 lbs) | B28: 21-35 lbs | C28: 1.075 | J28: Bikki Bear
A29: Large (36-85 lbs) | B29: 36-85 lbs | C29: 1.11 | J29: Black Russian Terrier
A30: Extra Large (86-100 lbs) | B30: 86-100 lbs | C30: 1.25 | J30: Bloodhound
A31: XXL (101 lbs+) | B31: 101 lbs+ | C31: 1.3 | J31: Blue Heeler
J32: Bolognese
J33: Border Collie
A34: AGE SURCHARGE (flat fee, applies per service) | J34: Border Terrier
A35: Condition | B35: Add-On Fee | J35: Borzoi
A36: Dog, 10 years or older | B36: 5 | J36: Boston Terrier
A37: Cat, 12 years or older | B37: 6 | J37: Bouvier de Flandres
J38: Boxer
J39: Boykin Spaniel
A40: STANDARD SERVICES (base $22, coat-type multiplier applies, rounded to nearest $ — confirmed) | J40: Briard
A41: Service | J41: Brittany Spaniel
A42: Profile Cut | J42: Brussels Griffon
A43: Puppy Cut | J43: Bull Terrier
A44: Shave Down | J44: Bulldog American
A45: Deshedding Service | J45: Bullmastiff
J46: Cairn Terrier
J47: Cane Corso
A48: ⚠ COAT TYPES REQUIRING PROFILE CUT (Shave Down unsafe) — interim list, pending final confirmation | J48: Catahoula Cur
A49: Coat Type | J49: Cattle Dog
A50: Long Feathered Sporting / Spaniel Coat | J50: Caucasian Shepherd
A51: Curly / Wool Coat | J51: Cavachon
A52: Single-layered Curly/Woolly Coat | J52: Cavalier King Charles Spaniel
A53: Long Double Coat | J53: Cavapoo
A54: Doodle / Mixed Wool Coat | J54: Chesapeake Bay Retriever
A55: Note: Husky exception (Short Double Coat, light tidy only) cannot be applied without a breed-level field — pending confirmation. | J55: Chihuahua
J56: Chihuahua (Long Hair)
J57: Chinese Crested (Powder Puff)
A58: PREMIUM SERVICES (ADD-ONS) | J58: Chinese Crested: Hairless
A59: Add-On | B59: Fee | C59: Time Added (min) | J59: Chow Chow
A60: Hot Aloe SPA Treatment (0-30 lbs) | B60: 20 | C60: 15 | J60: Clumber Spaniel
A61: Hot Aloe SPA Treatment (31-60 lbs) | B61: 25 | C61: 15 | J61: Cock A Poo
A62: Hot Aloe SPA Treatment (60+ lbs) | B62: 30 | C62: 15 | J62: Cocker Spaniel
A63: De-Shedding Treatment (0-30 lbs) | B63: 20 | C63: 15 | J63: Collie (Rough)
A64: De-Shedding Treatment (30-60 lbs) | B64: 25 | C64: 15 | J64: Collie (Smooth Coat)
A65: De-Shedding Treatment (60-100 lbs) | B65: 30 | C65: 15 | J65: Coon Hound
A66: De-Shedding Treatment (101+ lbs) | B66: 40 | C66: 15 | J66: Corgi
A67: Flea Clean-Up & Van Fumigation | B67: 30 | C67: 15 | J67: Coton De Tulear (like Havanese)
A68: Flea Elimination Shampoo | B68: 20 | C68: 15 | J68: Dachshund (Longhaired)
A69: Flea & Tick Treatment Drops | B69: 30 | C69: 15 | J69: Dachshund: (Smooth)
A70: Flea Removal | B70: 20 | C70: 15 | J70: Dachshund: (Wirehaired)
A71: Nail Trim - Extra (Dog) | B71: 10 | C71: 15 | J71: Dalmatian
... A77: Whitening Shampoo | B77: 10 | C77: 15 | J77: Doodle Standard
J78: Doodle X Large
J79: English Bulldog
A80: DE-MATTING (time-based, estimate only — final charge confirmed on-site) | J80: English Mastiff
A81: Time Bracket | B81: Cost | C81: Minutes Added | J81: English Setter
A82: First 15 minutes (included in base) | B82: 0 | C82: 0 | J82: English Toy Spaniel
A83: 16-30 minutes additional | B83: 15 | C83: 30 | J83: Eurasier
A84: 31-45 minutes additional | B84: 30 | C84: 45 | J84: Flat Coat Retriever
A85: 46-60 minutes additional | B85: 50 | C85: 60 | J85: Fox Terrier
J86: Foxhound (American)
J87: French Bulldog
A88: SEASONAL HOLIDAY PACKAGE SPECIAL ⚠ sample price shown — edit directly on this tab | J88: French Spaniel
A89: Item | B89: Price | J89: German Shepherd
A90: Seasonal Holiday Package Special | B90: 30 | J90: German Shepherd Long Hair
J91: German Shorthaired Pointer
J92: German Wirehaired Pointer
A93: SPECIES | J93: Glen of Immal Terrier
A94: Species | J94: Golden Retriever
A95: Dog | J95: Golden Retriever Extra Large
A96: Cat | J96: Golden Retriever Large
J97: Goldendoodle
A98: 🔒 SHEET PASSWORD (Pricing Calculator + Booking Log) | J98: Goldendoodle Extra Large
A99: Password: | B99: Demo2026 | J99: Goldendoodle Large
A100: Needed only to unprotect and edit formulas/layout (Review tab → Unprotect Sheet). Not needed for normal day-to-day use of dropdowns. | J100: Goldendoodle Medium
J101: Goldendoodle Miniature
A102: ⚠ Resolved (sample): Cat base time = 90 min (same as dogs). Standard Service ('haircut') adds +30 min, not 15. Age surcharge applies ONLY once, to Base Groom — not Standard Service or Premium Add-ons. Profile Cut priced at Shave Down price + $7. Seasonal Holiday Package = $25 for Fall (sample value). | J102: Gordon Setter
J103: Grand Basset Griffon Vendéen
A104: ⚠ STILL OPEN: Husky exception for Profile Cut. Client's breed list includes Huskies ('light tidy only, never shave'), but Huskies fall under 'Short Double Coat' in our coat-type system alongside other breeds where shaving IS fine. Cannot be safely implemented without a breed-level field. Needs direct input on how to handle this — see coat-type list above for which categories currently qualify for Profile Cut. | J104: Great Dane
J105: Great Pyrenees
...
